odoo/addons/nutritional_info/README.rst
odoo/addons/nutritional_info/__init__.py
odoo/addons/nutritional_info/__manifest__.py
odoo/addons/nutritional_info/i18n/es.po
odoo/addons/nutritional_info/i18n/nutritional_info.pot
odoo/addons/nutritional_info/models/__init__.py
odoo/addons/nutritional_info/models/nutritional_type.py
odoo/addons/nutritional_info/models/nutritional_value.py
odoo/addons/nutritional_info/models/product_product.py
odoo/addons/nutritional_info/models/product_template.py
odoo/addons/nutritional_info/readme/CONFIGURE.rst
odoo/addons/nutritional_info/readme/CONTRIBUTORS.rst
odoo/addons/nutritional_info/readme/DESCRIPTION.rst
odoo/addons/nutritional_info/readme/USAGE.rst
odoo/addons/nutritional_info/report/report_nutritional_info.xml
odoo/addons/nutritional_info/security/ir.model.access.csv
odoo/addons/nutritional_info/static/description/icon.png
odoo/addons/nutritional_info/static/description/index.html
odoo/addons/nutritional_info/static/src/scss/nutrition_table_style.scss
odoo/addons/nutritional_info/views/nutritional_type_view.xml
odoo/addons/nutritional_info/views/product_views.xml
odoo/addons/nutritional_info/views/res_config_settings_view.xml
odoo_addon_nutritional_info-15.0.1.0.0.6.dist-info/METADATA
odoo_addon_nutritional_info-15.0.1.0.0.6.dist-info/WHEEL
odoo_addon_nutritional_info-15.0.1.0.0.6.dist-info/top_level.txt
odoo_addon_nutritional_info-15.0.1.0.0.6.dist-info/RECORD
